[
{"name":"Classic FM","city":"Kathmandu","tags":["classic"],"favorites":5627,"rating":"+11","comments":0,"url":"https://radiovolna.net/en/423079-classic-fm.html","streamUrl":"https://radio-streaming-serv-1.hamropatro.com/radio/8060/radio.mp3"},
{"name":"Hits FM","city":"Kathmandu","tags":["hits"],"favorites":12160,"rating":"+4","comments":5,"url":"https://radiovolna.net/en/27693-hits-fm-912.html","streamUrl":"https://usa15.fastcast4u.com/proxy/hitsfm912?mp=/1"},
{"name":"City","city":"Kathmandu","tags":["indian-music"],"favorites":6965,"rating":"+2","comments":0,"url":"https://radiovolna.net/en/423078-city.html","streamUrl":"https://onlineradio.websoftitnepal.com/8036/stream;"},
{"name":"Nepal","city":"Kathmandu","tags":["talk"],"favorites":9039,"rating":"+2","comments":0,"url":"https://radiovolna.net/en/405520-nepal.html","streamUrl":"https://radionepal.news/live/"},
{"name":"Annapurna","city":"Kathmandu","tags":["folklore","news","talk"],"favorites":11287,"rating":"+2","comments":1,"url":"https://radiovolna.net/en/27348-citizen-fm-940.html","streamUrl":"http://streaming.softnep.net:8091/;stream.nsv"},
{"name":"Nepal FM","city":"Kathmandu","tags":["indian-music"],"favorites":6486,"rating":"+1","comments":0,"url":"https://radiovolna.net/en/423076-nepal-fm.html","streamUrl":"http://streaming.hamropatro.com:8230/;"},
{"name":"Kantipur","city":"Kathmandu","tags":["pop"],"favorites":8867,"rating":"+1","comments":0,"url":"https://radiovolna.net/en/405516-kantipur.html","streamUrl":"https://radio-broadcast.ekantipur.com/stream"},
{"name":"Navajyoti FM","city":"Kathmandu","tags":["indian-music"],"favorites":5388,"rating":"+1","comments":0,"url":"https://radiovolna.net/en/423075-navajyoti-fm.html","streamUrl":"http://live.itechnepal.com:8288/stream?type=.mp3"},
{"name":"Kalika FM","city":"Bharatpur","tags":["top-40","hits"],"favorites":9426,"rating":"+1","comments":0,"url":"https://radiovolna.net/en/27619-kalika-fm-952.html","streamUrl":"http://kalika-stream.softnep.com:7740/;stream.nsv"},
{"name":"Ujyaalo 90 Network","city":"Kathmandu","tags":["folklore"],"favorites":8132,"rating":"+1","comments":0,"url":"https://radiovolna.net/en/405512-ujyaalo-90-network.html","streamUrl":"https://stream.zenolive.com/wtuvp08xq1duv"},
{"name":"Mithila","city":"Janakpur","tags":["folklore"],"favorites":10212,"rating":"+1","comments":0,"url":"https://radiovolna.net/en/405517-mithila-janakpurdham.html","streamUrl":"http://streaming.hamropatro.com:8244/;"},
{"name":"BFBS Gurkha Radio","city":"Kathmandu","tags":["talk"],"favorites":6263,"rating":"+1","comments":0,"url":"https://radiovolna.net/en/423082-bfbs-gurkha-radio.html","streamUrl":"https://direct.sharp-stream.com/ssvcbfbs3.mp3"},
{"name":"Image FM","city":"Kathmandu","tags":["talk"],"favorites":7177,"rating":"+1","comments":0,"url":"https://radiovolna.net/en/423077-image-fm.html","streamUrl":"https://radio-streaming-serv-1.hamropatro.com/radio/8040/radio.mp3"},
{"name":"Good News FM","city":"Kathmandu","tags":["religion"],"favorites":8263,"rating":"+1","comments":0,"url":"https://radiovolna.net/en/405522-good-news-fm.html","streamUrl":"http://live.itechnepal.com:8162/stream"},
{"name":"Jayaprithvi F.M.","city":"Kathmandu","tags":["country"],"favorites":2128,"rating":"0","comments":0,"url":"https://radiovolna.net/en/430939-jayaprithvi-fm.html","streamUrl":"https://streaming.softnep.net:10824/;"},
{"name":"Capital FM","city":"Kathmandu","tags":["talk"],"favorites":7094,"rating":"0","comments":0,"url":"https://radiovolna.net/en/405513-capital-fm.html","streamUrl":"http://streaming.softnep.net:8037/;"},
{"name":"Times FM","city":"Kathmandu","tags":["pop"],"favorites":3103,"rating":"0","comments":0,"url":"https://radiovolna.net/en/428467-times-fm.html","streamUrl":"https://streaming.webhostnepal.com/8028/;"},
{"name":"STAR FM","city":"Kathmandu","tags":["folklore"],"favorites":8172,"rating":"0","comments":0,"url":"https://radiovolna.net/en/405515-star-fm.html","streamUrl":"http://live.itechnepal.com:9539/stream?type=.mp3"},
{"name":"KEEPS FM","city":"Kathmandu","tags":["indian-music"],"favorites":7076,"rating":"0","comments":0,"url":"https://radiovolna.net/en/405519-keeps-fm.html","streamUrl":"https://radio-streaming-serv-1.hamropatro.com/radio/8280/radio.mp3"},
{"name":"Radio Kathmandu","city":"Kathmandu","tags":["talk"],"favorites":14172,"rating":"0","comments":0,"url":"https://radiovolna.net/en/428468-radio-kathmandu.html","streamUrl":"http://95.217.153.73:8064/;"},
{"name":"Jayaprithvi F.M.","city":"Kathmandu","tags":["country"],"favorites":537,"rating":"0","comments":0,"url":"https://radiovolna.net/en/431635-jayaprithvi-fm.html","streamUrl":"https://streaming.softnep.net:10824/"},
{"name":"Radio Mithila","city":"Kathmandu","tags":["talk","pop"],"favorites":8155,"rating":"0","comments":0,"url":"https://radiovolna.net/en/405518-headlines-and-music-fm.html","streamUrl":"http://streaming.hamropatro.com:8246/;"},
{"name":"Bhaktapur","city":"Kathmandu","tags":["talk"],"favorites":5822,"rating":"0","comments":0,"url":"https://radiovolna.net/en/423081-bhaktapur.html","streamUrl":"https://streaming.softnep.net:10846/;stream.mp3"},
{"name":"Image News FM","city":"Kathmandu","tags":["news"],"favorites":7365,"rating":"0","comments":0,"url":"https://radiovolna.net/en/405521-image-news-fm.html","streamUrl":"https://radio-streaming-serv-1.hamropatro.com/radio/8050/radio.mp3"},
{"name":"Janasanchar","city":"Kathmandu","tags":["news"],"favorites":2927,"rating":"0","comments":0,"url":"https://radiovolna.net/en/428470-janasanchar.html","streamUrl":"https://online.net.np/8116/stream"},
{"name":"Nepaliko Radio","city":"Kathmandu","tags":["pop"],"favorites":2787,"rating":"0","comments":0,"url":"https://radiovolna.net/en/428465-nepaliko-radio.html","streamUrl":"https://streaming.webhostnepal.com/9888/;"},
{"name":"Sagarmatha","city":"Kathmandu","tags":["talk"],"favorites":6183,"rating":"0","comments":0,"url":"https://radiovolna.net/en/423080-sagarmatha.html","streamUrl":"http://143.95.89.54:9322/;"},
{"name":"Kool FM","city":"Kathmandu","tags":["pop"],"favorites":3321,"rating":"0","comments":0,"url":"https://radiovolna.net/en/428466-kool-fm.html","streamUrl":"http://streaming.softnep.net:8059/;"},
{"name":"Audio","city":"Kathmandu","tags":["talk"],"favorites":8955,"rating":"0","comments":0,"url":"https://radiovolna.net/en/30580-radio-audio-1063-fm.html","streamUrl":"https://stream.zenolive.com/2w81t82wx3duv"},
{"name":"Mero FM","city":"Kathmandu","tags":["folklore"],"favorites":7696,"rating":"-1","comments":0,"url":"https://radiovolna.net/en/405514-mero-fm.html","streamUrl":"http://streaming.hamropatro.com:8553/;"},
{"name":"Newa FM","city":"Kathmandu","tags":["talk"],"favorites":3311,"rating":"-1","comments":0,"url":"https://radiovolna.net/en/428469-newa-fm.html","streamUrl":"http://216.55.141.189:8683/;"}]